blockpaca/__init__.py
blockpaca/core.py
blockpaca/live_display.py
blockpaca/tools.py
blockpaca-0.1.2.dist-info/licenses/LICENSE
blockpaca-0.1.2.dist-info/METADATA
blockpaca-0.1.2.dist-info/WHEEL
blockpaca-0.1.2.dist-info/top_level.txt
blockpaca-0.1.2.dist-info/RECORD
