Metadata-Version: 2.4
Name: blockpaca
Version: 0.1.2
Summary: Parallel order execution for Alpaca
License: MIT
Project-URL: Homepage, https://github.com/henrysalkever/blockpaca
Requires-Python: >=3.10
License-File: LICENSE
Requires-Dist: aiohttp>=3.10.0
Requires-Dist: numpy>=1.26.0
Requires-Dist: polars>=1.12.0
Requires-Dist: websocket-client>=1.6.0
Requires-Dist: pyzmq>=25.0.0
Requires-Dist: rich>=13.9.0
Requires-Dist: alpaca-py>=0.10.0
Requires-Dist: pandas-market-calendars>=4.0.0
Dynamic: license-file
